certbot_dns_clouddns/__init__.py
certbot_dns_clouddns/dns_clouddns.py
certbot_dns_clouddns-1.0.0.post2.dist-info/entry_points.txt
certbot_dns_clouddns-1.0.0.post2.dist-info/LICENSE
certbot_dns_clouddns-1.0.0.post2.dist-info/WHEEL
certbot_dns_clouddns-1.0.0.post2.dist-info/METADATA
certbot_dns_clouddns-1.0.0.post2.dist-info/RECORD
