Metadata-Version: 2.1
Name: certbot-dns-clouddns
Version: 1.0.0.post2
Summary: CloudDNS Authenticator plugin for Certbot
Home-page: https://github.com/vshosting/certbot-dns-clouddns
License: Apache-2.0
Author: Radek SPRTA
Author-email: sprta@vshosting.cz
Requires-Python: >=2.7, !=3.0.*, !=3.1.*, !=3.2.*, !=3.3.*, !=3.4.*
Classifier: Development Status :: 5 - Production/Stable
Classifier: Environment :: Plugins
Classifier: Intended Audience :: System Administrators
Classifier: License :: OSI Approved :: Apache Software License
Classifier: Natural Language :: English
Classifier: Operating System :: POSIX :: Linux
Classifier: Programming Language :: Python
Classifier: Programming Language :: Python :: 2
Classifier: Programming Language :: Python :: 2.7
Classifier: Programming Language :: Python :: 3
Classifier: Programming Language :: Python :: 3.5
Classifier: Programming Language :: Python :: 3.6
Classifier: Programming Language :: Python :: 3.7
Classifier: Programming Language :: Python :: 3.8
Classifier: Programming Language :: Python :: 3.9
Classifier: Topic :: Internet :: WWW/HTTP
Classifier: Topic :: Security
Classifier: Topic :: System :: Installation/Setup
Classifier: Topic :: System :: Networking
Classifier: Topic :: System :: Systems Administration
Classifier: Topic :: Utilities
Requires-Dist: acme
Requires-Dist: certbot
Requires-Dist: requests
Project-URL: Documentation, https://github.com/vshosting/certbot-dns-clouddns
Project-URL: Repository, https://github.com/vshosting/certbot-dns-clouddns
